duong_test/__init__.py
duong_test/code.py
duong_test-0.0.1.dist-info/LICENSE
duong_test-0.0.1.dist-info/METADATA
duong_test-0.0.1.dist-info/WHEEL
duong_test-0.0.1.dist-info/top_level.txt
duong_test-0.0.1.dist-info/RECORD
