Metadata-Version: 2.1
Name: duong_test
Version: 0.0.1
Summary: A duong test package
Author-email: Dao Duong <nguyenduongyht@gmail.com>
Classifier: Programming Language :: Python :: 3
Classifier: License :: OSI Approved :: MIT License
Classifier: Operating System :: OS Independent
Requires-Python: >=3.8
License-File: LICENSE
